README.md
pyproject.toml
setup.py
cucounter/__init__.py
cucounter/counter.py
cucounter.egg-info/PKG-INFO
cucounter.egg-info/SOURCES.txt
cucounter.egg-info/dependency_links.txt
cucounter.egg-info/not-zip-safe
cucounter.egg-info/top_level.txt