Metadata-Version: 2.1
Name: cucounter
Version: 1.0.0
Summary: A hashtable based counter implemented in CUDA for high throughput.
Home-page: UNKNOWN
Author: Jørgen Henriksen
License: UNKNOWN
Platform: UNKNOWN
